{
  "code": 200,
  "time": 1621654987671,
  "data": {
    "current_leverage": -1.2130811712356793,
    "balance": {
      "btc": 1.02063487,
      "usd": 0
    },
    "account_unrealized_pnl": 0.41875739,
    "margin_balance": 1.43939226,
    "market_value": 52923.086700458836,
    "symbol": "BTCUSD_PERP",
    "exchange_max_leverge": "2",
    "position": {
      "qty": -64200,
      "avg_price": "48367.36162259",
      "unrealized_pnl": "0.41835431",
      "max_long_qty": 79384,
      "max_short_qty": -132308
    }
  }
}