{
  "code": 200,
  "time": 1619383869691,
  "data": {
    "current_leverage": -0.4601258392867009,
    "balance": {
      "btc": 1.08268148,
      "usd": 0
    },
    "account_unrealized_pnl": 0.05573932,
    "margin_balance": 1.1384208,
    "market_value": 55202.289963492905,
    "symbol": "BTCUSD_PERP",
    "exchange_max_leverge": "2",
    "position": {
      "qty": -25400,
      "avg_price": "54212.42693789",
      "unrealized_pnl": "0.05573932",
      "max_long_qty": 82803,
      "max_short_qty": -138006
    }
  }
}