{
  "code": 200,
  "time": 1618327688573,
  "data": {
    "current_leverage": -1.157063927274751,
    "balance": {
      "btc": 1.33409783,
      "usd": 0
    },
    "account_unrealized_pnl": -0.14256009,
    "margin_balance": 1.19153774,
    "market_value": 75103.88834321091,
    "symbol": "BTCUSD_PERP",
    "exchange_max_leverge": "2",
    "position": {
      "qty": -86900,
      "avg_price": "57169.28775501",
      "unrealized_pnl": "-0.14256009",
      "max_long_qty": 112655,
      "max_short_qty": -187760
    }
  }
}