{
  "code": 200,
  "time": 1622650269024,
  "data": {
    "current_leverage": -0.775292005608277,
    "balance": {
      "btc": 1.22957873,
      "usd": 0
    },
    "account_unrealized_pnl": 0.18978342,
    "margin_balance": 1.41936215,
    "market_value": 54173.13695508536,
    "symbol": "BTCUSD_PERP",
    "exchange_max_leverge": "2",
    "position": {
      "qty": -42000,
      "avg_price": "46135.89589794",
      "unrealized_pnl": "0.18978342",
      "max_long_qty": 81259,
      "max_short_qty": -135433
    }
  }
}