{
  "code": 200,
  "time": 1617173708203,
  "data": {
    "current_leverage": -0.5509057403446899,
    "balance": {
      "btc": 1.30405233,
      "usd": 0
    },
    "account_unrealized_pnl": -0.05147284,
    "margin_balance": 1.25257949,
    "market_value": 74785.93338711999,
    "symbol": "BTCUSD_PERP",
    "exchange_max_leverge": "2",
    "position": {
      "qty": -41200,
      "avg_price": "55659.38992142",
      "unrealized_pnl": "-0.05147284",
      "max_long_qty": 112178,
      "max_short_qty": -186965
    }
  }
}