{
  "code": 200,
  "time": 1620820328213,
  "data": {
    "current_leverage": 0.1361029443092214,
    "balance": {
      "btc": 1.05560819,
      "usd": 0
    },
    "account_unrealized_pnl": -0.00179385,
    "margin_balance": 1.05381434,
    "market_value": 59513.774967256155,
    "symbol": "BTCUSD_PERP",
    "exchange_max_leverge": "2",
    "position": {
      "qty": 8100,
      "avg_price": "57215.92472027",
      "unrealized_pnl": "-0.00179385",
      "max_long_qty": 89270,
      "max_short_qty": -148785
    }
  }
}