{
  "code": 200,
  "time": 1617165308919,
  "data": {
    "current_leverage": -0.5552927442582233,
    "balance": {
      "btc": 1.30405233,
      "usd": 0
    },
    "account_unrealized_pnl": -0.03812849,
    "margin_balance": 1.26592384,
    "market_value": 74195.09875828864,
    "symbol": "BTCUSD_PERP",
    "exchange_max_leverge": "2",
    "position": {
      "qty": -41200,
      "avg_price": "55659.38992142",
      "unrealized_pnl": "-0.03812849",
      "max_long_qty": 111292,
      "max_short_qty": -185488
    }
  }
}