{
  "code": 200,
  "time": 1623959467894,
  "data": {
    "current_leverage": -0.45774257132329743,
    "balance": {
      "btc": 1.31956933,
      "usd": 0
    },
    "account_unrealized_pnl": 0.12023257,
    "margin_balance": 1.4398019,
    "market_value": 54397.38743987931,
    "symbol": "BTCUSD_PERP",
    "exchange_max_leverge": "2",
    "position": {
      "qty": -24900,
      "avg_price": "46135.89589794",
      "unrealized_pnl": "0.12023273",
      "max_long_qty": 81596,
      "max_short_qty": -135994
    }
  }
}