{
  "code": 200,
  "time": 1617941469388,
  "data": {
    "current_leverage": -0.9665763528067117,
    "balance": {
      "btc": 1.31848673,
      "usd": 0
    },
    "account_unrealized_pnl": -0.02997858,
    "margin_balance": 1.28850815,
    "market_value": 74800.09188105803,
    "symbol": "BTCUSD_PERP",
    "exchange_max_leverge": "2",
    "position": {
      "qty": -72300,
      "avg_price": "56711.61286627",
      "unrealized_pnl": "-0.02997858",
      "max_long_qty": 112200,
      "max_short_qty": -187001
    }
  }
}