{
  "code": 200,
  "time": 1620111068538,
  "data": {
    "current_leverage": -0.1771713587947886,
    "balance": {
      "btc": 1.06162756,
      "usd": 0
    },
    "account_unrealized_pnl": -0.00491223,
    "margin_balance": 1.05671533,
    "market_value": 59264.65807693998,
    "symbol": "BTCUSD_PERP",
    "exchange_max_leverge": "2",
    "position": {
      "qty": -10500,
      "avg_price": "54656.39300052",
      "unrealized_pnl": "-0.00491223",
      "max_long_qty": 88896,
      "max_short_qty": -148162
    }
  }
}