{
  "code": 200,
  "time": 1621181768374,
  "data": {
    "current_leverage": -1.1764827185557787,
    "balance": {
      "btc": 1.02681477,
      "usd": 0
    },
    "account_unrealized_pnl": 0.02545666,
    "margin_balance": 1.05227143,
    "market_value": 50489.479414468566,
    "symbol": "BTCUSD_PERP",
    "exchange_max_leverge": "2",
    "position": {
      "qty": -59400,
      "avg_price": "49049.84733076",
      "unrealized_pnl": "0.02545666",
      "max_long_qty": 75734,
      "max_short_qty": -126224
    }
  }
}