{
  "code": 200,
  "time": 1617631087717,
  "data": {
    "current_leverage": -0.7838577864936199,
    "balance": {
      "btc": 1.31282982,
      "usd": 0
    },
    "account_unrealized_pnl": -0.03047508,
    "margin_balance": 1.28235474,
    "market_value": 74503.31042986372,
    "symbol": "BTCUSD_PERP",
    "exchange_max_leverge": "2",
    "position": {
      "qty": -58400,
      "avg_price": "56444.75210109",
      "unrealized_pnl": "-0.03049546",
      "max_long_qty": 111754,
      "max_short_qty": -186259
    }
  }
}