{
  "code": 200,
  "time": 1624641668287,
  "data": {
    "current_leverage": -0.95826009535589,
    "balance": {
      "btc": 1.34816816,
      "usd": 0
    },
    "account_unrealized_pnl": 0.1995963,
    "margin_balance": 1.54776446,
    "market_value": 49673.36136680277,
    "symbol": "BTCUSD_PERP",
    "exchange_max_leverge": "2",
    "position": {
      "qty": -47600,
      "avg_price": "37060.83797984",
      "unrealized_pnl": "0.19959630",
      "max_long_qty": 74510,
      "max_short_qty": -124184
    }
  }
}