{
  "code": 200,
  "time": 1622767208808,
  "data": {
    "current_leverage": -0.6640444436224711,
    "balance": {
      "btc": 1.2571655,
      "usd": 0
    },
    "account_unrealized_pnl": 0.15029217,
    "margin_balance": 1.40745767,
    "market_value": 54514.423466181084,
    "symbol": "BTCUSD_PERP",
    "exchange_max_leverge": "2",
    "position": {
      "qty": -36200,
      "avg_price": "46135.89589794",
      "unrealized_pnl": "0.15029217",
      "max_long_qty": 81771,
      "max_short_qty": -136287
    }
  }
}