{
  "code": 200,
  "time": 1618194968318,
  "data": {
    "current_leverage": -1.1025148526807185,
    "balance": {
      "btc": 1.32866605,
      "usd": 0
    },
    "account_unrealized_pnl": -0.06739544,
    "margin_balance": 1.26127061,
    "market_value": 75373.13424662339,
    "symbol": "BTCUSD_PERP",
    "exchange_max_leverge": "2",
    "position": {
      "qty": -83100,
      "avg_price": "57047.59043897",
      "unrealized_pnl": "-0.06739544",
      "max_long_qty": 113059,
      "max_short_qty": -188433
    }
  }
}