{
  "code": 200,
  "time": 1620296648224,
  "data": {
    "current_leverage": -0.09591884568900393,
    "balance": {
      "btc": 1.06092838,
      "usd": 0
    },
    "account_unrealized_pnl": -0.00699819,
    "margin_balance": 1.05393019,
    "market_value": 61510.33154766553,
    "symbol": "BTCUSD_PERP",
    "exchange_max_leverge": "2",
    "position": {
      "qty": -5900,
      "avg_price": "54656.39300052",
      "unrealized_pnl": "-0.00699819",
      "max_long_qty": 92265,
      "max_short_qty": -153776
    }
  }
}