{
  "code": 200,
  "time": 1621618689029,
  "data": {
    "current_leverage": -1.1984531127833986,
    "balance": {
      "btc": 1.02085028,
      "usd": 0
    },
    "account_unrealized_pnl": 0.41690436,
    "margin_balance": 1.43775464,
    "market_value": 52901.527246864054,
    "symbol": "BTCUSD_PERP",
    "exchange_max_leverge": "2",
    "position": {
      "qty": -63400,
      "avg_price": "48546.17156645",
      "unrealized_pnl": "0.41653528",
      "max_long_qty": 79352,
      "max_short_qty": -132254
    }
  }
}