{
  "code": 200,
  "time": 1623027187592,
  "data": {
    "current_leverage": -0.6310779627485222,
    "balance": {
      "btc": 1.27296628,
      "usd": 0
    },
    "account_unrealized_pnl": 0.19784103,
    "margin_balance": 1.47080731,
    "market_value": 53400.692131962605,
    "symbol": "BTCUSD_PERP",
    "exchange_max_leverge": "2",
    "position": {
      "qty": -33700,
      "avg_price": "46135.89589794",
      "unrealized_pnl": "0.19784103",
      "max_long_qty": 80101,
      "max_short_qty": -133502
    }
  }
}