{
  "code": 200,
  "time": 1618259527839,
  "data": {
    "current_leverage": -1.102011048957587,
    "balance": {
      "btc": 1.33129281,
      "usd": 0
    },
    "account_unrealized_pnl": -0.07599316,
    "margin_balance": 1.25529965,
    "market_value": 75407.59239991818,
    "symbol": "BTCUSD_PERP",
    "exchange_max_leverge": "2",
    "position": {
      "qty": -83100,
      "avg_price": "57047.59043897",
      "unrealized_pnl": "-0.07599316",
      "max_long_qty": 113111,
      "max_short_qty": -188519
    }
  }
}