{
  "code": 200,
  "time": 1621617969304,
  "data": {
    "current_leverage": -1.1983906744136923,
    "balance": {
      "btc": 2.33886855,
      "usd": 0
    },
    "account_unrealized_pnl": 0.65726913,
    "margin_balance": 2.33886855,
    "market_value": 87008.35397522905,
    "symbol": "BTC-PERPETUAL",
    "exchange_max_leverge": "unlimited",
    "position": {
      "qty": -104270,
      "avg_price": 48571.75,
      "unrealized_pnl": 0.65726913,
      "max_long_qty": 130512,
      "max_short_qty": -217521
    }
  }
}