{
  "code": 200,
  "time": 1619930588315,
  "data": {
    "current_leverage": -0.7496424910446555,
    "balance": {
      "btc": 1.73697095,
      "usd": 0
    },
    "account_unrealized_pnl": -0.0501765,
    "margin_balance": 1.73697095,
    "market_value": 98526.96569677269,
    "symbol": "BTC-PERPETUAL",
    "exchange_max_leverge": "unlimited",
    "position": {
      "qty": -73860,
      "avg_price": 54638.94,
      "unrealized_pnl": -0.050176503,
      "max_long_qty": 147790,
      "max_short_qty": -246318
    }
  }
}