{
  "code": 200,
  "time": 1617655448019,
  "data": {
    "current_leverage": -0.7806771743095227,
    "balance": {
      "btc": 2.08890991,
      "usd": 0
    },
    "account_unrealized_pnl": -0.07348975,
    "margin_balance": 2.08890991,
    "market_value": 123059.82954474111,
    "symbol": "BTC-PERPETUAL",
    "exchange_max_leverge": "unlimited",
    "position": {
      "qty": -96070,
      "avg_price": 56450.98,
      "unrealized_pnl": -0.073489748,
      "max_long_qty": 184589,
      "max_short_qty": -307650
    }
  }
}