{
  "code": 200,
  "time": 1621474988780,
  "data": {
    "current_leverage": -1.1815056591173492,
    "balance": {
      "btc": 2.35551574,
      "usd": 0
    },
    "account_unrealized_pnl": 0.67258288,
    "margin_balance": 2.35551574,
    "market_value": 87176.89941235386,
    "symbol": "BTC-PERPETUAL",
    "exchange_max_leverge": "unlimited",
    "position": {
      "qty": -103000,
      "avg_price": 48685.24,
      "unrealized_pnl": 0.672582877,
      "max_long_qty": 130765,
      "max_short_qty": -217943
    }
  }
}