{
  "code": 200,
  "time": 1620231849501,
  "data": {
    "current_leverage": -0.13452442966765693,
    "balance": {
      "btc": 1.73885131,
      "usd": 0
    },
    "account_unrealized_pnl": -0.01262541,
    "margin_balance": 1.73885131,
    "market_value": 100130.51185779179,
    "symbol": "BTC-PERPETUAL",
    "exchange_max_leverge": "unlimited",
    "position": {
      "qty": -13470,
      "avg_price": 54638.94,
      "unrealized_pnl": -0.012625405,
      "max_long_qty": 150195,
      "max_short_qty": -250327
    }
  }
}