{
  "code": 200,
  "time": 1618727348278,
  "data": {
    "current_leverage": 0.821283822213305,
    "balance": {
      "btc": 1.7854118,
      "usd": 0
    },
    "account_unrealized_pnl": -0.15980907,
    "margin_balance": 1.7854118,
    "market_value": 100355.07551808777,
    "symbol": "BTC-PERPETUAL",
    "exchange_max_leverge": "unlimited",
    "position": {
      "qty": 82420,
      "avg_price": 63119.85,
      "unrealized_pnl": -0.159809069,
      "max_long_qty": 150532,
      "max_short_qty": -250888
    }
  }
}