{
  "code": 200,
  "time": 1624928768728,
  "data": {
    "current_leverage": -0.9689802204739114,
    "balance": {
      "btc": 2.33981491,
      "usd": 0
    },
    "account_unrealized_pnl": 0.11004807,
    "margin_balance": 2.33981491,
    "market_value": 81663.17364176834,
    "symbol": "BTC-PERPETUAL",
    "exchange_max_leverge": "unlimited",
    "position": {
      "qty": -79130,
      "avg_price": 36695.88,
      "unrealized_pnl": 0.110048065,
      "max_long_qty": 122494,
      "max_short_qty": -204158
    }
  }
}