{
  "code": 200,
  "time": 1620984488769,
  "data": {
    "current_leverage": -1.154901961032503,
    "balance": {
      "btc": 1.62689646,
      "usd": 0
    },
    "account_unrealized_pnl": -0.06281374,
    "margin_balance": 1.62689646,
    "market_value": 82431.23937108002,
    "symbol": "BTC-PERPETUAL",
    "exchange_max_leverge": "unlimited",
    "position": {
      "qty": -95200,
      "avg_price": 49092.6,
      "unrealized_pnl": -0.062813739,
      "max_long_qty": 123646,
      "max_short_qty": -206079
    }
  }
}