{
  "code": 200,
  "time": 1624539670584,
  "data": {
    "current_leverage": -0.9552878709209612,
    "balance": {
      "btc": 2.4169209,
      "usd": 0
    },
    "account_unrealized_pnl": 0.19139349,
    "margin_balance": 2.4169209,
    "market_value": 82142.77851591446,
    "symbol": "BTC-PERPETUAL",
    "exchange_max_leverge": "unlimited",
    "position": {
      "qty": -78470,
      "avg_price": 37027.19,
      "unrealized_pnl": 0.191393491,
      "max_long_qty": 123214,
      "max_short_qty": -205357
    }
  }
}