{
  "code": 200,
  "time": 1621912089435,
  "data": {
    "current_leverage": -1.2696220679183867,
    "balance": {
      "btc": 2.27668435,
      "usd": 0
    },
    "account_unrealized_pnl": 0.59326846,
    "margin_balance": 2.27668435,
    "market_value": 86403.66513151352,
    "symbol": "BTC-PERPETUAL",
    "exchange_max_leverge": "unlimited",
    "position": {
      "qty": -109700,
      "avg_price": 47832.9,
      "unrealized_pnl": 0.593268462,
      "max_long_qty": 129605,
      "max_short_qty": -216010
    }
  }
}