{
  "code": 200,
  "time": 1619638379982,
  "data": {
    "current_leverage": -0.5710540223243911,
    "balance": {
      "btc": 1.77258111,
      "usd": 0
    },
    "account_unrealized_pnl": -0.01382581,
    "margin_balance": 1.77258111,
    "market_value": 97433.86409139646,
    "symbol": "BTC-PERPETUAL",
    "exchange_max_leverge": "unlimited",
    "position": {
      "qty": -55640,
      "avg_price": 54225.46,
      "unrealized_pnl": -0.013825806,
      "max_long_qty": 146150,
      "max_short_qty": -243585
    }
  }
}