{
  "code": 200,
  "time": 1620490988746,
  "data": {
    "current_leverage": -0.021174547858299787,
    "balance": {
      "btc": 1.73995213,
      "usd": 0
    },
    "account_unrealized_pnl": -0.00254785,
    "margin_balance": 1.73995213,
    "market_value": 101536.99688833093,
    "symbol": "BTC-PERPETUAL",
    "exchange_max_leverge": "unlimited",
    "position": {
      "qty": -2150,
      "avg_price": 54638.94,
      "unrealized_pnl": -0.002547847,
      "max_long_qty": 152305,
      "max_short_qty": -253843
    }
  }
}