{
  "code": 200,
  "time": 1618224848497,
  "data": {
    "current_leverage": -1.1018442636882735,
    "balance": {
      "btc": 2.07831378,
      "usd": 0
    },
    "account_unrealized_pnl": -0.11090376,
    "margin_balance": 2.07831378,
    "market_value": 124046.56856176964,
    "symbol": "BTC-PERPETUAL",
    "exchange_max_leverge": "unlimited",
    "position": {
      "qty": -136680,
      "avg_price": 57056.77,
      "unrealized_pnl": -0.110903759,
      "max_long_qty": 186069,
      "max_short_qty": -310117
    }
  }
}