{
  "code": 200,
  "time": 1623986348565,
  "data": {
    "current_leverage": -0.43998405684483644,
    "balance": {
      "btc": 2.372362,
      "usd": 0
    },
    "account_unrealized_pnl": 0.18778945,
    "margin_balance": 2.372362,
    "market_value": 89866.89264048508,
    "symbol": "BTC-PERPETUAL",
    "exchange_max_leverge": "unlimited",
    "position": {
      "qty": -39540,
      "avg_price": 46152.26,
      "unrealized_pnl": 0.187789451,
      "max_long_qty": 134800,
      "max_short_qty": -224668
    }
  }
}