{
  "code": 200,
  "time": 1618412770602,
  "data": {
    "current_leverage": 0.4886632973739793,
    "balance": {
      "btc": 1.94249762,
      "usd": 0
    },
    "account_unrealized_pnl": -0.00338306,
    "margin_balance": 1.94249762,
    "market_value": 122722.53783386624,
    "symbol": "BTC-PERPETUAL",
    "exchange_max_leverge": "unlimited",
    "position": {
      "qty": 59970,
      "avg_price": 63527,
      "unrealized_pnl": -0.00338306,
      "max_long_qty": 184083,
      "max_short_qty": -306807
    }
  }
}