{
  "code": 200,
  "time": 1622977148880,
  "data": {
    "current_leverage": -0.6476394337015453,
    "balance": {
      "btc": 2.43772028,
      "usd": 0
    },
    "account_unrealized_pnl": 0.34494597,
    "margin_balance": 2.43772028,
    "market_value": 87811.20642231873,
    "symbol": "BTC-PERPETUAL",
    "exchange_max_leverge": "unlimited",
    "position": {
      "qty": -56870,
      "avg_price": 46152.26,
      "unrealized_pnl": 0.344945965,
      "max_long_qty": 131716,
      "max_short_qty": -219529
    }
  }
}