{
  "code": 200,
  "time": 1620051788918,
  "data": {
    "current_leverage": -0.20874487126653624,
    "balance": {
      "btc": 1.72974238,
      "usd": 0
    },
    "account_unrealized_pnl": -0.02233803,
    "margin_balance": 1.72974238,
    "market_value": 100265.93646593356,
    "symbol": "BTC-PERPETUAL",
    "exchange_max_leverge": "unlimited",
    "position": {
      "qty": -20930,
      "avg_price": 54638.94,
      "unrealized_pnl": -0.022338025,
      "max_long_qty": 150398,
      "max_short_qty": -250665
    }
  }
}