{
  "code": 200,
  "time": 1621864270154,
  "data": {
    "current_leverage": -1.2505640159835307,
    "balance": {
      "btc": 2.29247261,
      "usd": 0
    },
    "account_unrealized_pnl": 0.60951738,
    "margin_balance": 2.29247261,
    "market_value": 86640.9065151183,
    "symbol": "BTC-PERPETUAL",
    "exchange_max_leverge": "unlimited",
    "position": {
      "qty": -108350,
      "avg_price": 47968.3,
      "unrealized_pnl": 0.609517375,
      "max_long_qty": 129961,
      "max_short_qty": -216603
    }
  }
}