{
  "code": 200,
  "time": 1617887049630,
  "data": {
    "current_leverage": -0.9210350426290131,
    "balance": {
      "btc": 2.14176228,
      "usd": 0
    },
    "account_unrealized_pnl": -0.02632778,
    "margin_balance": 2.14176228,
    "market_value": 122916.06156140602,
    "symbol": "BTC-PERPETUAL",
    "exchange_max_leverge": "unlimited",
    "position": {
      "qty": -113210,
      "avg_price": 56643.02,
      "unrealized_pnl": -0.026327783,
      "max_long_qty": 184374,
      "max_short_qty": -307291
    }
  }
}