{
  "code": 200,
  "time": 1617281770161,
  "data": {
    "current_leverage": -0.5992802939795958,
    "balance": {
      "btc": 2.09069392,
      "usd": 0
    },
    "account_unrealized_pnl": -0.06229705,
    "margin_balance": 2.09069392,
    "market_value": 122546.99635176137,
    "symbol": "BTC-PERPETUAL",
    "exchange_max_leverge": "unlimited",
    "position": {
      "qty": -73440,
      "avg_price": 55908.04,
      "unrealized_pnl": -0.062297046,
      "max_long_qty": 183820,
      "max_short_qty": -306368
    }
  }
}