{
  "code": 200,
  "time": 1621385528663,
  "data": {
    "current_leverage": -1.1974026580247452,
    "balance": {
      "btc": 1.98815068,
      "usd": 0
    },
    "account_unrealized_pnl": 0.2997505,
    "margin_balance": 1.98815068,
    "market_value": 84950.53799846992,
    "symbol": "BTC-PERPETUAL",
    "exchange_max_leverge": "unlimited",
    "position": {
      "qty": -101720,
      "avg_price": 48874.86,
      "unrealized_pnl": 0.299750501,
      "max_long_qty": 127425,
      "max_short_qty": -212377
    }
  }
}