{
  "code": 200,
  "time": 1616529548853,
  "data": {
    "current_leverage": -0.19740924871665438,
    "balance": {
      "btc": 2.15545482,
      "usd": 0
    },
    "account_unrealized_pnl": 0.01205821,
    "margin_balance": 2.15545482,
    "avaliable_balance": 2.15119291,
    "market_value": 118535.47973117768,
    "symbol": "BTC-PERPETUAL",
    "exchange_max_leverge": "unlimited",
    "contract_value": -0.425286596,
    "position": {
      "qty": -23400,
      "avg_price": 56627.28,
      "unrealized_pnl": 0.01205821,
      "max_long_qty": 177803,
      "max_short_qty": -296339
    }
  }
}