{
  "code": 200,
  "time": 1617713049717,
  "data": {
    "current_leverage": -0.824254349718384,
    "balance": {
      "btc": 2.09686317,
      "usd": 0
    },
    "account_unrealized_pnl": -0.06882976,
    "margin_balance": 2.09686317,
    "market_value": 123287.1868188741,
    "symbol": "BTC-PERPETUAL",
    "exchange_max_leverge": "unlimited",
    "position": {
      "qty": -101620,
      "avg_price": 56604.14,
      "unrealized_pnl": -0.06882976,
      "max_long_qty": 184930,
      "max_short_qty": -308218
    }
  }
}