{
  "code": 200,
  "time": 1616518688965,
  "data": {
    "current_leverage": -0.19602758937790904,
    "balance": {
      "btc": 2.15177716,
      "usd": 0
    },
    "account_unrealized_pnl": 0.00838966,
    "margin_balance": 2.15177716,
    "avaliable_balance": 2.1475521,
    "market_value": 119370.95219228881,
    "symbol": "BTC-PERPETUAL",
    "exchange_max_leverge": "unlimited",
    "contract_value": -0.421618051,
    "position": {
      "qty": -23400,
      "avg_price": 56627.28,
      "unrealized_pnl": 0.008389665,
      "max_long_qty": 179056,
      "max_short_qty": -298428
    }
  }
}