{
  "code": 200,
  "time": 1623975788390,
  "data": {
    "current_leverage": -0.4386951646766117,
    "balance": {
      "btc": 2.36786991,
      "usd": 0
    },
    "account_unrealized_pnl": 0.18320744,
    "margin_balance": 2.36786991,
    "market_value": 90130.92275395214,
    "symbol": "BTC-PERPETUAL",
    "exchange_max_leverge": "unlimited",
    "position": {
      "qty": -39540,
      "avg_price": 46152.26,
      "unrealized_pnl": 0.183207435,
      "max_long_qty": 135196,
      "max_short_qty": -225328
    }
  }
}