{
  "code": 200,
  "time": 1617043869384,
  "data": {
    "current_leverage": -0.46734103122459797,
    "balance": {
      "btc": 2.09933728,
      "usd": 0
    },
    "account_unrealized_pnl": -0.04645442,
    "margin_balance": 2.09933728,
    "market_value": 121217.68947091392,
    "symbol": "BTC-PERPETUAL",
    "exchange_max_leverge": "unlimited",
    "position": {
      "qty": -56650,
      "avg_price": 55193.84,
      "unrealized_pnl": -0.046454424,
      "max_long_qty": 181826,
      "max_short_qty": -303045
    }
  }
}