{
  "code": 200,
  "time": 1624524249010,
  "data": {
    "current_leverage": -0.9574715684272551,
    "balance": {
      "btc": 2.48451175,
      "usd": 0
    },
    "account_unrealized_pnl": 0.25897225,
    "margin_balance": 2.48451175,
    "market_value": 81955.43615868928,
    "symbol": "BTC-PERPETUAL",
    "exchange_max_leverge": "unlimited",
    "position": {
      "qty": -78470,
      "avg_price": 37027.19,
      "unrealized_pnl": 0.258972251,
      "max_long_qty": 122933,
      "max_short_qty": -204889
    }
  }
}