{
  "code": 200,
  "time": 1618950611602,
  "data": {
    "current_leverage": -0.18818527561674134,
    "balance": {
      "btc": 1.78181153,
      "usd": 0
    },
    "account_unrealized_pnl": -0.00464952,
    "margin_balance": 1.78181153,
    "market_value": 101442.58065587845,
    "symbol": "BTC-PERPETUAL",
    "exchange_max_leverge": "unlimited",
    "position": {
      "qty": -19090,
      "avg_price": 56197.08,
      "unrealized_pnl": -0.004562055,
      "max_long_qty": 152163,
      "max_short_qty": -253607
    }
  }
}