{
  "code": 200,
  "time": 1619323328939,
  "data": {
    "current_leverage": -0.4524480725850212,
    "balance": {
      "btc": 1.85495002,
      "usd": 0
    },
    "account_unrealized_pnl": 0.06843725,
    "margin_balance": 1.85495002,
    "market_value": 92319.98660387893,
    "symbol": "BTC-PERPETUAL",
    "exchange_max_leverge": "unlimited",
    "position": {
      "qty": -41770,
      "avg_price": 54189.12,
      "unrealized_pnl": 0.068437248,
      "max_long_qty": 138479,
      "max_short_qty": -230800
    }
  }
}