{
  "code": 200,
  "time": 1617410826299,
  "data": {
    "current_leverage": 0.31207514993160085,
    "balance": {
      "btc": 0,
      "usd": 134182.65314998
    },
    "account_unrealized_pnl": 0.0,
    "margin_balance": 0.0,
    "market_value": 134182.65314998,
    "symbol": "BTC-PERP",
    "exchange_max_leverge": "unlimited",
    "position": {
      "qty": 0.7053,
      "avg_price": 46698.24289725408,
      "unrealized_pnl": 85494.9007,
      "max_long_qty": 5,
      "max_short_qty": -4
    }
  }
}