{
  "code": 200,
  "time": 1623387186649,
  "data": {
    "current_leverage": 0.43962463962257436,
    "balance": {
      "btc": 0,
      "usd": 92888.99078782
    },
    "account_unrealized_pnl": 0.0,
    "margin_balance": 0.0,
    "market_value": 92888.99078782,
    "symbol": "BTC-PERP",
    "exchange_max_leverge": "unlimited",
    "position": {
      "qty": 1.1027,
      "avg_price": 36203.70381917381,
      "unrealized_pnl": 876.1945,
      "max_long_qty": 6,
      "max_short_qty": -4
    }
  }
}