{
  "code": 200,
  "time": 1623453667320,
  "data": {
    "current_leverage": 0.4403330115441391,
    "balance": {
      "btc": 0,
      "usd": 92962.4359901
    },
    "account_unrealized_pnl": 0.0,
    "margin_balance": 0.0,
    "market_value": 92962.4359901,
    "symbol": "BTC-PERP",
    "exchange_max_leverge": "unlimited",
    "position": {
      "qty": 1.1027,
      "avg_price": 36203.70381917381,
      "unrealized_pnl": 961.1024,
      "max_long_qty": 6,
      "max_short_qty": -4
    }
  }
}