{
  "code": 200,
  "time": 1624090689132,
  "data": {
    "current_leverage": -0.43680605303975395,
    "balance": {
      "btc": 1.12078771206,
      "usd": 0
    },
    "account_unrealized_pnl": 0.11063109222732814,
    "margin_balance": 1.2314138303428745,
    "market_value": 43957.724180741854,
    "symbol": "pi_xbtusd",
    "exchange_max_leverge": "unlimited",
    "position": {
      "qty": -19201,
      "avg_price": 44935.384337365045,
      "unrealized_pnl": 0.11063109222732814,
      "max_long_qty": 65936,
      "max_short_qty": -109895
    }
  }
}