{
  "code": 200,
  "time": 1621698370361,
  "data": {
    "current_leverage": -1.2250883166595323,
    "balance": {
      "btc": 0.89285495055,
      "usd": 0
    },
    "account_unrealized_pnl": 0.24722122425250756,
    "margin_balance": 1.1400717710855341,
    "market_value": 43837.65584055056,
    "symbol": "pi_xbtusd",
    "exchange_max_leverge": "unlimited",
    "position": {
      "qty": -53705,
      "avg_price": 46760.89757644042,
      "unrealized_pnl": 0.24722122425250756,
      "max_long_qty": 65756,
      "max_short_qty": -109595
    }
  }
}