{
  "code": 200,
  "time": 1618200189206,
  "data": {
    "current_leverage": -1.1031385283750592,
    "balance": {
      "btc": 1.19338811315,
      "usd": 0
    },
    "account_unrealized_pnl": -0.07412592736989813,
    "margin_balance": 1.1192711300782001,
    "market_value": 67582.62727874963,
    "symbol": "pi_xbtusd",
    "exchange_max_leverge": "unlimited",
    "position": {
      "qty": -74553,
      "avg_price": 57043.410421016495,
      "unrealized_pnl": -0.07412592736989813,
      "max_long_qty": 101373,
      "max_short_qty": -168957
    }
  }
}