{
  "code": 200,
  "time": 1623647470434,
  "data": {
    "current_leverage": -0.4979283574033093,
    "balance": {
      "btc": 1.10678720043,
      "usd": 0
    },
    "account_unrealized_pnl": 0.07465982196988531,
    "margin_balance": 1.1814267792518611,
    "market_value": 46358.074724600105,
    "symbol": "pi_xbtusd",
    "exchange_max_leverge": "unlimited",
    "position": {
      "qty": -23083,
      "avg_price": 44935.384337365045,
      "unrealized_pnl": 0.07465982196988531,
      "max_long_qty": 69537,
      "max_short_qty": -115896
    }
  }
}