{
  "code": 200,
  "time": 1619029030118,
  "data": {
    "current_leverage": -0.23764092953528132,
    "balance": {
      "btc": 0.96955825864,
      "usd": 0
    },
    "account_unrealized_pnl": 0.002590354085139969,
    "margin_balance": 0.9721448402742437,
    "market_value": 53963.76804735603,
    "symbol": "pi_xbtusd",
    "exchange_max_leverge": "unlimited",
    "position": {
      "qty": -12824,
      "avg_price": 56139.725882136794,
      "unrealized_pnl": 0.002590354085139969,
      "max_long_qty": 80945,
      "max_short_qty": -134910
    }
  }
}