{
  "code": 200,
  "time": 1623263530758,
  "data": {
    "current_leverage": -0.5963318111836565,
    "balance": {
      "btc": 1.09080126451,
      "usd": 0
    },
    "account_unrealized_pnl": 0.14163547651398473,
    "margin_balance": 1.2323779936216412,
    "market_value": 44745.22321228684,
    "symbol": "pi_xbtusd",
    "exchange_max_leverge": "unlimited",
    "position": {
      "qty": -26683,
      "avg_price": 44935.384337365045,
      "unrealized_pnl": 0.14163547651398473,
      "max_long_qty": 67117,
      "max_short_qty": -111864
    }
  }
}