{
  "code": 200,
  "time": 1623100329694,
  "data": {
    "current_leverage": -0.6412869778273083,
    "balance": {
      "btc": 1.08107665995,
      "usd": 0
    },
    "account_unrealized_pnl": 0.19074621151663046,
    "margin_balance": 1.271838101965055,
    "market_value": 43816.57662096916,
    "symbol": "pi_xbtusd",
    "exchange_max_leverge": "unlimited",
    "position": {
      "qty": -28099,
      "avg_price": 44935.384337365045,
      "unrealized_pnl": 0.19074621151663046,
      "max_long_qty": 65724,
      "max_short_qty": -109542
    }
  }
}