{
  "current_leverage": -0.6945299870724063,
  "balance": {
    "btc": 1.17264219281,
    "usd": 0
  },
  "account_unrealized_pnl": -0.011879467336496898,
  "margin_balance": 1.1607627305825066,
  "market_value": 66280.79543986752,
  "symbol": "pi_xbtusd",
  "exchange_max_leverge": "unlimited",
  "position": {
    "qty": -46034,
    "avg_price": 56286.1369379425,
    "unrealized_pnl": -0.011879467336496898,
    "max_long_qty": 99421,
    "max_short_qty": -165702
  },
  "timestamp": 1617494400000,
  "index_price": 57179
}