{
  "code": 200,
  "time": 1620926229820,
  "data": {
    "current_leverage": -1.22212746189196,
    "balance": {
      "btc": 0.90891139805,
      "usd": 0
    },
    "account_unrealized_pnl": -0.03323266879948162,
    "margin_balance": 0.8756555399705337,
    "market_value": 42561.02707934919,
    "symbol": "pi_xbtusd",
    "exchange_max_leverge": "unlimited",
    "position": {
      "qty": -52015,
      "avg_price": 47173.53323686401,
      "unrealized_pnl": -0.03323266879948162,
      "max_long_qty": 63841,
      "max_short_qty": -106403
    }
  }
}