{
  "code": 200,
  "time": 1621714989793,
  "data": {
    "current_leverage": -1.221057756249459,
    "balance": {
      "btc": 0.8927937231,
      "usd": 0
    },
    "account_unrealized_pnl": 0.26622979429551025,
    "margin_balance": 1.1590093351213295,
    "market_value": 43982.35851263715,
    "symbol": "pi_xbtusd",
    "exchange_max_leverge": "unlimited",
    "position": {
      "qty": -53705,
      "avg_price": 46760.89757644042,
      "unrealized_pnl": 0.26622979429551025,
      "max_long_qty": 65973,
      "max_short_qty": -109956
    }
  }
}