{
  "code": 200,
  "time": 1621336690357,
  "data": {
    "current_leverage": -1.1958834962813216,
    "balance": {
      "btc": 0.90423913457,
      "usd": 0
    },
    "account_unrealized_pnl": 0.04299151584594615,
    "margin_balance": 0.9469341669246732,
    "market_value": 42943.14635137265,
    "symbol": "pi_xbtusd",
    "exchange_max_leverge": "unlimited",
    "position": {
      "qty": -51355,
      "avg_price": 47148.545048470114,
      "unrealized_pnl": 0.04299151584594615,
      "max_long_qty": 64414,
      "max_short_qty": -107358
    }
  }
}