{
  "code": 200,
  "time": 1622131390490,
  "data": {
    "current_leverage": -1.3185952164133175,
    "balance": {
      "btc": 0.89100200911,
      "usd": 0
    },
    "account_unrealized_pnl": 0.20603996276914505,
    "margin_balance": 1.0970452310024277,
    "market_value": 43365.08982304426,
    "symbol": "pi_xbtusd",
    "exchange_max_leverge": "unlimited",
    "position": {
      "qty": -57181,
      "avg_price": 46096.484086725904,
      "unrealized_pnl": 0.20603996276914505,
      "max_long_qty": 65047,
      "max_short_qty": -108413
    }
  }
}