{
  "code": 200,
  "time": 1624066508768,
  "data": {
    "current_leverage": -0.43353117115222684,
    "balance": {
      "btc": 1.12095211047,
      "usd": 0
    },
    "account_unrealized_pnl": 0.10397780938580023,
    "margin_balance": 1.2249017253735477,
    "market_value": 44289.77955372419,
    "symbol": "pi_xbtusd",
    "exchange_max_leverge": "unlimited",
    "position": {
      "qty": -19201,
      "avg_price": 44935.384337365045,
      "unrealized_pnl": 0.10397780938580023,
      "max_long_qty": 66434,
      "max_short_qty": -110725
    }
  }
}