{
  "code": 200,
  "time": 1622105771021,
  "data": {
    "current_leverage": -1.3133251425059063,
    "balance": {
      "btc": 0.89112892417,
      "usd": 0
    },
    "account_unrealized_pnl": 0.22484256930750576,
    "margin_balance": 1.1159230771984001,
    "market_value": 43539.10402636097,
    "symbol": "pi_xbtusd",
    "exchange_max_leverge": "unlimited",
    "position": {
      "qty": -57181,
      "avg_price": 46096.484086725904,
      "unrealized_pnl": 0.22484256930750576,
      "max_long_qty": 65308,
      "max_short_qty": -108848
    }
  }
}