{
  "code": 200,
  "time": 1621012270285,
  "data": {
    "current_leverage": -1.1537339725510523,
    "balance": {
      "btc": 0.90560466955,
      "usd": 0
    },
    "account_unrealized_pnl": -0.07427924145726132,
    "margin_balance": 0.831292566164609,
    "market_value": 42284.444387236144,
    "symbol": "pi_xbtusd",
    "exchange_max_leverge": "unlimited",
    "position": {
      "qty": -48785,
      "avg_price": 47173.53323686401,
      "unrealized_pnl": -0.07427924145726132,
      "max_long_qty": 63426,
      "max_short_qty": -105712
    }
  }
}