{
  "code": 200,
  "time": 1617365229178,
  "data": {
    "current_leverage": -0.6414033950313769,
    "balance": {
      "btc": 1.16973744765,
      "usd": 0
    },
    "account_unrealized_pnl": -0.043848984252785855,
    "margin_balance": 1.1258976638834906,
    "market_value": 66907.97138343903,
    "symbol": "pi_xbtusd",
    "exchange_max_leverge": "unlimited",
    "position": {
      "qty": -42915,
      "avg_price": 56094.23262214591,
      "unrealized_pnl": -0.043848984252785855,
      "max_long_qty": 100361,
      "max_short_qty": -167270
    }
  }
}