{
  "code": 200,
  "time": 1620398229971,
  "data": {
    "current_leverage": -0.05963053433217763,
    "balance": {
      "btc": 0.94869222642,
      "usd": 0
    },
    "account_unrealized_pnl": -0.002717205612122433,
    "margin_balance": 0.9459835642812813,
    "market_value": 54066.260450399415,
    "symbol": "pi_xbtusd",
    "exchange_max_leverge": "unlimited",
    "position": {
      "qty": -3224,
      "avg_price": 54569.29678359739,
      "unrealized_pnl": -0.002717205612122433,
      "max_long_qty": 81099,
      "max_short_qty": -135166
    }
  }
}