{
  "code": 200,
  "time": 1618223770476,
  "data": {
    "current_leverage": -1.099141185539096,
    "balance": {
      "btc": 1.19407242937,
      "usd": 0
    },
    "account_unrealized_pnl": -0.059667527609699345,
    "margin_balance": 1.1350421225288287,
    "market_value": 67828.41092742237,
    "symbol": "pi_xbtusd",
    "exchange_max_leverge": "unlimited",
    "position": {
      "qty": -74553,
      "avg_price": 57043.410421016495,
      "unrealized_pnl": -0.059667527609699345,
      "max_long_qty": 101742,
      "max_short_qty": -169572
    }
  }
}