{
  "code": 200,
  "time": 1617054310893,
  "data": {
    "current_leverage": -0.4682399396502821,
    "balance": {
      "btc": 1.16260575634,
      "usd": 0
    },
    "account_unrealized_pnl": -0.02366749935673734,
    "margin_balance": 1.1390248482517191,
    "market_value": 65541.18391293345,
    "symbol": "pi_xbtusd",
    "exchange_max_leverge": "unlimited",
    "position": {
      "qty": -30689,
      "avg_price": 55176.96785868225,
      "unrealized_pnl": -0.02366749935673734,
      "max_long_qty": 98311,
      "max_short_qty": -163853
    }
  }
}