{
  "code": 200,
  "time": 1624403109291,
  "data": {
    "current_leverage": -0.4053482713704139,
    "balance": {
      "btc": 1.13590415982,
      "usd": 0
    },
    "account_unrealized_pnl": 0.1431972492010684,
    "margin_balance": 1.278976110747959,
    "market_value": 41633.33407823623,
    "symbol": "pi_xbtusd",
    "exchange_max_leverge": "unlimited",
    "position": {
      "qty": -16876,
      "avg_price": 44935.384337365045,
      "unrealized_pnl": 0.1431972492010684,
      "max_long_qty": 62450,
      "max_short_qty": -104084
    }
  }
}