{
  "code": 200,
  "time": 1624665909650,
  "data": {
    "current_leverage": -0.9606660114133044,
    "balance": {
      "btc": 1.13155752048,
      "usd": 0
    },
    "account_unrealized_pnl": 0.18190011519383428,
    "margin_balance": 1.3134528642874572,
    "market_value": 41275.53127612489,
    "symbol": "pi_xbtusd",
    "exchange_max_leverge": "unlimited",
    "position": {
      "qty": -39652,
      "avg_price": 36727.846050731096,
      "unrealized_pnl": 0.18190011519383428,
      "max_long_qty": 61913,
      "max_short_qty": -103189
    }
  }
}