{
  "code": 200,
  "time": 1618739529345,
  "data": {
    "current_leverage": 0.8734687502713968,
    "balance": {
      "btc": 1.05903314814,
      "usd": 0
    },
    "account_unrealized_pnl": -0.11462616342557257,
    "margin_balance": 0.9445582527971508,
    "market_value": 51364.17300110614,
    "symbol": "pi_xbtusd",
    "exchange_max_leverge": "unlimited",
    "position": {
      "qty": 44865,
      "avg_price": 63175.34103372488,
      "unrealized_pnl": -0.11462616342557257,
      "max_long_qty": 77046,
      "max_short_qty": -128411
    }
  }
}