{
  "code": 200,
  "time": 1622362212064,
  "data": {
    "current_leverage": -0.7345552981544056,
    "balance": {
      "btc": 2.33755455,
      "usd": 0
    },
    "account_unrealized_pnl": -0.15774253,
    "margin_balance": 2.17981202,
    "market_value": 78062.19646644869,
    "symbol": "BTC-SWAP",
    "exchange_max_leverge": 0.73,
    "position": {
      "qty": -57341,
      "avg_price": 32582.4,
      "unrealized_pnl": -0.15774253,
      "max_long_qty": 117093,
      "max_short_qty": -195156
    }
  }
}