{
  "code": 200,
  "time": 1621920791079,
  "data": {
    "current_leverage": -1.2712029054216039,
    "balance": {
      "btc": 2.46146494,
      "usd": 0
    },
    "account_unrealized_pnl": -0.453388,
    "margin_balance": 2.00807694,
    "market_value": 76455.9297225378,
    "symbol": "BTC-SWAP",
    "exchange_max_leverge": 1.27,
    "position": {
      "qty": -97191,
      "avg_price": 32334.4,
      "unrealized_pnl": -0.453388,
      "max_long_qty": 114683,
      "max_short_qty": -191140
    }
  }
}