{
  "code": 200,
  "time": 1616892849959,
  "data": {
    "current_leverage": -0.6230416774696274,
    "balance": {
      "btc": 1.80325268,
      "usd": 0
    },
    "account_unrealized_pnl": 0.00620513,
    "margin_balance": 1.8094578099999998,
    "market_value": 101272.51880846433,
    "symbol": "BTC-SWAP",
    "exchange_max_leverge": 0.62,
    "position": {
      "qty": -63097,
      "avg_price": 56290.6,
      "unrealized_pnl": 0.00620513,
      "max_long_qty": 151908,
      "max_short_qty": -253182
    }
  }
}