{
  "code": 200,
  "time": 1624189029682,
  "data": {
    "current_leverage": -0.4313577796700963,
    "balance": {
      "btc": 2.23453412,
      "usd": 0
    },
    "account_unrealized_pnl": -0.0324165,
    "margin_balance": 2.20211762,
    "market_value": 74745.37731685,
    "symbol": "BTC-SWAP",
    "exchange_max_leverge": 0.67,
    "position": {
      "qty": -32242,
      "avg_price": 32813.6,
      "unrealized_pnl": -0.0324165,
      "max_long_qty": 112118,
      "max_short_qty": -186864
    }
  }
}