{
  "code": 200,
  "time": 1623060131554,
  "data": {
    "current_leverage": -0.6290207116236567,
    "balance": {
      "btc": 2.29335909,
      "usd": 0
    },
    "account_unrealized_pnl": -0.14586595,
    "margin_balance": 2.14749314,
    "market_value": 78084.8692139516,
    "symbol": "BTC-SWAP",
    "exchange_max_leverge": 0.66,
    "position": {
      "qty": -49117,
      "avg_price": 32813.6,
      "unrealized_pnl": -0.14586595,
      "max_long_qty": 117127,
      "max_short_qty": -195213
    }
  }
}