{
  "code": 200,
  "time": 1624746610481,
  "data": {
    "current_leverage": -1.0131547388241655,
    "balance": {
      "btc": 2.22906476,
      "usd": 0
    },
    "account_unrealized_pnl": 0.05600905,
    "margin_balance": 2.28507381,
    "market_value": 72066.9777301134,
    "symbol": "BTC-SWAP",
    "exchange_max_leverge": 1.13,
    "position": {
      "qty": -73015,
      "avg_price": 32302.9,
      "unrealized_pnl": 0.05600905,
      "max_long_qty": 108100,
      "max_short_qty": -180168
    }
  }
}