{
  "code": 200,
  "time": 1623403813782,
  "data": {
    "current_leverage": -0.5577108989221355,
    "balance": {
      "btc": 2.28321707,
      "usd": 0
    },
    "account_unrealized_pnl": -0.16443642,
    "margin_balance": 2.11878065,
    "market_value": 79177.222617206,
    "symbol": "BTC-SWAP",
    "exchange_max_leverge": 0.65,
    "position": {
      "qty": -44158,
      "avg_price": 32813.6,
      "unrealized_pnl": -0.16443642,
      "max_long_qty": 118765,
      "max_short_qty": -197944
    }
  }
}