{
  "code": 200,
  "time": 1622505911479,
  "data": {
    "current_leverage": -0.7604305288065887,
    "balance": {
      "btc": 2.33807454,
      "usd": 0
    },
    "account_unrealized_pnl": -0.23933118,
    "margin_balance": 2.09874336,
    "market_value": 78917.13670962238,
    "symbol": "BTC-SWAP",
    "exchange_max_leverge": 0.75,
    "position": {
      "qty": -60011,
      "avg_price": 32733.6,
      "unrealized_pnl": -0.23933118,
      "max_long_qty": 118375,
      "max_short_qty": -197293
    }
  }
}