{
  "code": 200,
  "time": 1620267069750,
  "data": {
    "current_leverage": -0.6368708477433347,
    "balance": {
      "btc": 1.59939293,
      "usd": 0
    },
    "account_unrealized_pnl": -0.03545593,
    "margin_balance": 1.5639370000000001,
    "market_value": 89264.56627971001,
    "symbol": "BTC-SWAP",
    "exchange_max_leverge": 0.63,
    "position": {
      "qty": -56850,
      "avg_price": 55123.6,
      "unrealized_pnl": -0.03545593,
      "max_long_qty": 133896,
      "max_short_qty": -223162
    }
  }
}