{
  "code": 200,
  "time": 1616872810549,
  "data": {
    "current_leverage": -0.5938009757348941,
    "balance": {
      "btc": 1.80313066,
      "usd": 0
    },
    "account_unrealized_pnl": 0.01078644,
    "margin_balance": 1.8139171,
    "market_value": 101104.582938246,
    "symbol": "BTC-SWAP",
    "exchange_max_leverge": 0.59,
    "position": {
      "qty": -60036,
      "avg_price": 56308.7,
      "unrealized_pnl": 0.01078644,
      "max_long_qty": 151656,
      "max_short_qty": -252762
    }
  }
}