{
  "code": 200,
  "time": 1617556749515,
  "data": {
    "current_leverage": -0.8262965666213525,
    "balance": {
      "btc": 1.81575953,
      "usd": 0
    },
    "account_unrealized_pnl": -0.03724995,
    "margin_balance": 1.77850958,
    "market_value": 103381.76806094033,
    "symbol": "BTC-SWAP",
    "exchange_max_leverge": 0.82,
    "position": {
      "qty": -85424,
      "avg_price": 56706.3,
      "unrealized_pnl": -0.03724995,
      "max_long_qty": 155072,
      "max_short_qty": -258455
    }
  }
}