{
  "code": 200,
  "time": 1617331270757,
  "data": {
    "current_leverage": -0.7627381347062209,
    "balance": {
      "btc": 1.81174593,
      "usd": 0
    },
    "account_unrealized_pnl": -0.08171846,
    "margin_balance": 1.73002747,
    "market_value": 103557.16648469784,
    "symbol": "BTC-SWAP",
    "exchange_max_leverge": 0.75,
    "position": {
      "qty": -78987,
      "avg_price": 56614.2,
      "unrealized_pnl": -0.08171846,
      "max_long_qty": 155335,
      "max_short_qty": -258893
    }
  }
}