{
  "code": 200,
  "time": 1621338250641,
  "data": {
    "current_leverage": -1.199915505933688,
    "balance": {
      "btc": 1.59861248,
      "usd": 0
    },
    "account_unrealized_pnl": 0.23010052,
    "margin_balance": 1.8287129999999998,
    "market_value": 83215.85937194999,
    "symbol": "BTC-SWAP",
    "exchange_max_leverge": 1.19,
    "position": {
      "qty": -99852,
      "avg_price": 50852.7,
      "unrealized_pnl": 0.23010052,
      "max_long_qty": 124823,
      "max_short_qty": -208040
    }
  }
}