{
  "code": 200,
  "time": 1624485610710,
  "data": {
    "current_leverage": -0.9098287665226003,
    "balance": {
      "btc": 2.23108874,
      "usd": 0
    },
    "account_unrealized_pnl": -0.0637238,
    "margin_balance": 2.16736494,
    "market_value": 72236.6696001444,
    "symbol": "BTC-SWAP",
    "exchange_max_leverge": 1.08,
    "position": {
      "qty": -65723,
      "avg_price": 32291.4,
      "unrealized_pnl": -0.0637238,
      "max_long_qty": 108355,
      "max_short_qty": -180592
    }
  }
}